tests/test_cli.py
whl_conf/__init__.py
whl_conf/cli.py
whl_conf/config.py
whl_conf/config_compare.py
whl_conf/confs_lock.py
whl_conf/meta.py
whl_conf/utils.py
whl_conf/data/__init__.py
whl_conf/data/default_template.yaml
whl_conf/data/meta.yaml
whl_conf/validator/existence.py
whl_conf/validator/transform.py
whl_conf-0.0.6.dist-info/licenses/LICENSE
whl_conf-0.0.6.dist-info/METADATA
whl_conf-0.0.6.dist-info/WHEEL
whl_conf-0.0.6.dist-info/entry_points.txt
whl_conf-0.0.6.dist-info/top_level.txt
whl_conf-0.0.6.dist-info/RECORD
